[
    {
      "body": "Great post! Thanks for sharing.",
      "post_id": 1
    },
    {
      "body": "I have a question about this topic. Can you provide more information?",
      "post_id": 1
    },
    {
      "body": "Awesome content. I learned a lot from this post.",
      "post_id": 2
    },
    {
      "body": "This is really helpful. I'll definitely try implementing these suggestions.",
      "post_id": 2
    },
    {
      "body": "I completely agree with your point of view. Well said!",
      "post_id": 3
    }
  ]
  